logger_aux/__init__.py
logger_aux/main.py
logger_aux-0.0.11.dist-info/LICENSE
logger_aux-0.0.11.dist-info/METADATA
logger_aux-0.0.11.dist-info/WHEEL
logger_aux-0.0.11.dist-info/top_level.txt
logger_aux-0.0.11.dist-info/RECORD
